kronbot/__init__.py
kronbot/__main__.py
kronbot/launcher.py
kronbot/logging.py
kronbot/meta.py
kronbot/py.typed
kronbot/setup.py
kronbot/cogs/__init__.py
kronbot/cogs/admin/__init__.py
kronbot/cogs/admin/admin.py
kronbot/cogs/admin/announcer.py
kronbot/cogs/admin/converters.py
kronbot/cogs/admin/locales/af-ZA.po
kronbot/cogs/admin/locales/ar-SA.po
kronbot/cogs/admin/locales/bg-BG.po
kronbot/cogs/admin/locales/ca-ES.po
kronbot/cogs/admin/locales/cs-CZ.po
kronbot/cogs/admin/locales/da-DK.po
kronbot/cogs/admin/locales/de-DE.po
kronbot/cogs/admin/locales/el-GR.po
kronbot/cogs/admin/locales/en-PT.po
kronbot/cogs/admin/locales/en-US.po
kronbot/cogs/admin/locales/es-ES.po
kronbot/cogs/admin/locales/fi-FI.po
kronbot/cogs/admin/locales/fr-FR.po
kronbot/cogs/admin/locales/he-IL.po
kronbot/cogs/admin/locales/hu-HU.po
kronbot/cogs/admin/locales/id-ID.po
kronbot/cogs/admin/locales/it-IT.po
kronbot/cogs/admin/locales/ja-JP.po
kronbot/cogs/admin/locales/ko-KR.po
kronbot/cogs/admin/locales/lol-US.po
kronbot/cogs/admin/locales/nl-NL.po
kronbot/cogs/admin/locales/no-NO.po
kronbot/cogs/admin/locales/pl-PL.po
kronbot/cogs/admin/locales/pt-BR.po
kronbot/cogs/admin/locales/pt-PT.po
kronbot/cogs/admin/locales/ro-RO.po
kronbot/cogs/admin/locales/ru-RU.po
kronbot/cogs/admin/locales/sk-SK.po
kronbot/cogs/admin/locales/sr-SP.po
kronbot/cogs/admin/locales/sv-SE.po
kronbot/cogs/admin/locales/tr-TR.po
kronbot/cogs/admin/locales/uk-UA.po
kronbot/cogs/admin/locales/vi-VN.po
kronbot/cogs/admin/locales/zh-CN.po
kronbot/cogs/admin/locales/zh-HK.po
kronbot/cogs/admin/locales/zh-TW.po
kronbot/cogs/alias/__init__.py
kronbot/cogs/alias/alias.py
kronbot/cogs/alias/alias_entry.py
kronbot/cogs/alias/locales/af-ZA.po
kronbot/cogs/alias/locales/ar-SA.po
kronbot/cogs/alias/locales/bg-BG.po
kronbot/cogs/alias/locales/ca-ES.po
kronbot/cogs/alias/locales/cs-CZ.po
kronbot/cogs/alias/locales/da-DK.po
kronbot/cogs/alias/locales/de-DE.po
kronbot/cogs/alias/locales/el-GR.po
kronbot/cogs/alias/locales/en-PT.po
Kr0nOs-3.4.1.dist-info/METADATA
Kr0nOs-3.4.1.dist-info/WHEEL
Kr0nOs-3.4.1.dist-info/entry_points.txt
Kr0nOs-3.4.1.dist-info/top_level.txt
Kr0nOs-3.4.1.dist-info/RECORD
